LICENCE
MANIFEST.in
README.rst
setup.py
music_story/__init__.py
music_story/api.py
music_story/exceptions.py
music_story/models.py
music_story/music_story_oauth.py
music_story.egg-info/PKG-INFO
music_story.egg-info/SOURCES.txt
music_story.egg-info/dependency_links.txt
music_story.egg-info/requires.txt
music_story.egg-info/top_level.txt
tests/__init__.py
tests/test_base.py