Metadata-Version: 1.1
Name: music-story
Version: 0.1
Summary: Music Story Python SDK
Home-page: http://developers.music-story.com
Author: Kevin Samuel
Author-email: kevin.samuel@yandex.com
License: UNKNOWN
Platform: UNKNOWN
Classifier: Programming Language :: Python
Classifier: Intended Audience :: Information Technology
Classifier: License :: OSI Approved :: BSD License
Classifier: Natural Language :: English
Classifier: Programming Language :: Python :: 2.7
Classifier: Programming Language :: Python :: 3.3
